tox_add_factor/__init__.py
tox_add_factor/envlist.py
tox_add_factor/hooks.py
tox_add_factor-0.1.0.dist-info/LICENSE
tox_add_factor-0.1.0.dist-info/METADATA
tox_add_factor-0.1.0.dist-info/WHEEL
tox_add_factor-0.1.0.dist-info/entry_points.txt
tox_add_factor-0.1.0.dist-info/top_level.txt
tox_add_factor-0.1.0.dist-info/version.txt
tox_add_factor-0.1.0.dist-info/RECORD
