Metadata-Version: 2.1
Name: tox-add-factor
Version: 0.1.0
Summary: Tox plugin to add factors
Home-page: https://github.com/jayvdb/tox-add-factor
Author: John Mark Vandenberg
Author-email: jayvdb@gmail.com
License: MIT
Platform: UNKNOWN
Classifier: Environment :: Console
Classifier: Framework :: tox
Classifier: Intended Audience :: Developers
Classifier: License :: OSI Approved :: MIT License
Classifier: Operating System :: OS Independent
Classifier: Programming Language :: Python :: 2.7
Classifier: Programming Language :: Python :: 3.4
Classifier: Programming Language :: Python :: 3.5
Classifier: Programming Language :: Python :: 3.6
Classifier: Programming Language :: Python :: 3.7
Classifier: Programming Language :: Python :: Implementation :: CPython
Classifier: Programming Language :: Python :: Implementation :: PyPy
Classifier: Topic :: Software Development :: Quality Assurance
Classifier: Topic :: Software Development :: Testing
Classifier: Development Status :: 4 - Beta
Requires-Python: >=2.7,!=3.0.*,!=3.1.*,!=3.2.*,!=3.3.*
Requires-Dist: py-cpuinfo
Requires-Dist: py-osinfo
Requires-Dist: tox (>=3.4)
